{"__type__":"cc.SpriteAtlas","_name":"faceprofesor1.plist","_spriteFrames":{"1":{"__uuid__":"a0FCJti3FEJ5cK8i/RUVbA"},"2":{"__uuid__":"b6X0g+tFtIAYwP1yDiPyJ3"},"3":{"__uuid__":"f0WNxTiClHzKlDDqaqJqTs"},"4":{"__uuid__":"cbJI4TZCpCXbawUaihdzXc"},"5":{"__uuid__":"2asDK6ChJMpKXj8E9v4kgO"},"6":{"__uuid__":"cdMsyRR1NF24ttBMfynr+a"},"7":{"__uuid__":"1fLi9kIb9PQojvu3xb7ABQ"},"8":{"__uuid__":"c4o9x6hf9IV6iMXjTYCZCO"},"9":{"__uuid__":"0dxpVe7bBBf4dROKUQD1rr"},"10":{"__uuid__":"afPakJo3tNwqGS1mXWx6y+"},"11":{"__uuid__":"edDLLBrPlOqITx4u9VQ7xB"},"12":{"__uuid__":"8bm8Gn/XhIP6UEknTkfk0e"},"13":{"__uuid__":"24Lcnn9+VEeLQDUt16T/q5"},"14":{"__uuid__":"f0R9p5fkRJJY9pBfgKaZBr"},"15":{"__uuid__":"c52bB1dAZHAas+ngB/iaJs"}}}